pygeo3d/__init__.py
pygeo3d-0.0.8.dist-info/LICENSE.txt
pygeo3d-0.0.8.dist-info/METADATA
pygeo3d-0.0.8.dist-info/WHEEL
pygeo3d-0.0.8.dist-info/top_level.txt
pygeo3d-0.0.8.dist-info/RECORD
