Metadata-Version: 2.1
Name: pygeo3d
Version: 0.0.8
Summary: provides a 3D co-ordinate system using Vectors in Python
Home-page: https://github.com/divyajeettt/pygeo3d
Author: Divyajeet Singh
Author-email: knightt1821@gmail.com
Classifier: Programming Language :: Python :: 3
Classifier: License :: OSI Approved :: MIT License
Classifier: Operating System :: OS Independent
License-File: LICENSE.txt
Requires-Dist: matplotlib
Requires-Dist: numpy
Requires-Dist: pyvectors
Requires-Dist: linear-equations
